simple_iptables/__init__.py
simple_iptables/securitygroup.py
simple_iptables-1.0.2.dist-info/METADATA
simple_iptables-1.0.2.dist-info/WHEEL
simple_iptables-1.0.2.dist-info/top_level.txt
simple_iptables-1.0.2.dist-info/RECORD
