Metadata-Version: 2.1
Name: simple_iptables
Version: 1.0.2
Summary: Simple Python client library for Iptables
Home-page: https://github.com/xizhendu/iptables
Author: Xizhen Du
Author-email: xizhendu@gmail.com
